[{"file_zip":"1528344-57778-gjk.zip","story_name":{},"thumb_end":{},"background":"","act_id":1528344,"id":1000162,"turn":[{"right_answer":[],"word":[{"path":"18c50572-fec0-4d60-8d70-2db9a26153bb_358200.zip","image":[],"word_id":40156156,"text":"cake","audio":[{"duration":0,"file_path":"880e7159-9205-4024-b1f2-0cfade6f9553.mp3","score":0,"voices_type_id":65,"tag_title":"cake","link":"audio/880e7159-9205-4024-b1f2-0cfade6f9553.mp3","name_original":"","voices_id":65,"id":255681,"sync_data":""}],"video":[],"type":"question","order":0},{"path":"ae432953-87cc-45f1-85f0-970201ef4b43_358201.zip","image":[],"word_id":40156157,"text":"c","audio":[{"duration":0,"file_path":"402ed20a-b076-4278-82c5-a80d7b12edf8.mp3","score":0,"voices_type_id":65,"tag_title":"c","link":"audio/402ed20a-b076-4278-82c5-a80d7b12edf8.mp3","name_original":"","voices_id":65,"id":255682,"sync_data":""}],"video":[],"type":"phonic","order":0},{"path":"7934d7a2-a65a-4b10-a3f3-3d25151c416e_358202.zip","image":[],"word_id":40156158,"text":"a_e","audio":[{"duration":0,"file_path":"1aaaced2-e7ab-4250-b726-b6e960400641.mp3","score":0,"voices_type_id":65,"tag_title":"a_e","link":"audio/1aaaced2-e7ab-4250-b726-b6e960400641.mp3","name_original":"","voices_id":65,"id":255683,"sync_data":""}],"video":[],"type":"phonic","order":0},{"path":"20e30abd-9f5d-40b9-aeb2-fb0a81609765_358203.zip","image":[],"word_id":40156159,"text":"k","audio":[{"duration":0,"file_path":"dea9dbe8-442d-4d1a-8445-f4878dbc565b.mp3","score":0,"voices_type_id":65,"tag_title":"k","link":"audio/dea9dbe8-442d-4d1a-8445-f4878dbc565b.mp3","name_original":"","voices_id":65,"id":255684,"sync_data":""}],"video":[],"type":"phonic","order":0}],"phonic":{},"order":1}],"thumb_start":{}},{"file_zip":"1528381-57793-jay.zip","story_name":{},"thumb_end":{},"background":"","act_id":1528381,"id":1000162,"turn":[{"right_answer":[],"word":[{"path":"9bea0899-a915-4c2b-8d15-0e9bdd9c03e6_357975.zip","image":[],"word_id":40155931,"text":"slug","audio":[{"duration":0,"file_path":"1b2cc150-d92b-42f5-adc9-89add1865fe6.mp3","score":0,"voices_type_id":65,"tag_title":"slug","link":"audio/1b2cc150-d92b-42f5-adc9-89add1865fe6.mp3","name_original":"","voices_id":65,"id":255460,"sync_data":""}],"video":[],"type":"question","order":0},{"path":"22199b27-56ff-45bb-a424-b29562d05a5d_357976.zip","image":[],"word_id":40155932,"text":"sl","audio":[{"duration":0,"file_path":"47d7e5c8-745d-4aa2-b311-6c7a012640d6.mp3","score":0,"voices_type_id":65,"tag_title":"sl","link":"audio/47d7e5c8-745d-4aa2-b311-6c7a012640d6.mp3","name_original":"","voices_id":65,"id":255461,"sync_data":""}],"video":[],"type":"phonic","order":0},{"path":"fa2deac1-10b4-4729-9b8f-31bb746875a2_357977.zip","image":[],"word_id":40155933,"text":"u","audio":[{"duration":0,"file_path":"74ae211b-d5a5-4fed-8e37-2ec200c20785.mp3","score":0,"voices_type_id":65,"tag_title":"u","link":"audio/74ae211b-d5a5-4fed-8e37-2ec200c20785.mp3","name_original":"","voices_id":65,"id":255462,"sync_data":""}],"video":[],"type":"phonic","order":0},{"path":"5db39377-87ca-4a3a-88c2-9903264234c6_357978.zip","image":[],"word_id":40155934,"text":"g","audio":[{"duration":0,"file_path":"97d9af45-843a-43a0-a1bd-1d10180e9327.mp3","score":0,"voices_type_id":65,"tag_title":"g","link":"audio/97d9af45-843a-43a0-a1bd-1d10180e9327.mp3","name_original":"","voices_id":65,"id":255463,"sync_data":""}],"video":[],"type":"phonic","order":0}],"phonic":{},"order":1}],"thumb_start":{}},{"file_zip":"1528395-57742-jxl.zip","story_name":{},"thumb_end":{},"background":"","act_id":1528395,"id":1000162,"turn":[{"right_answer":[],"word":[{"path":"22f78692-ea93-425e-b762-f5237c9369f8_358745.zip","image":[],"word_id":40156701,"text":"star","audio":[{"duration":0,"file_path":"1b23ea6b-b13b-4cd1-b1f4-ce5210f30408.mp3","score":0,"voices_type_id":65,"tag_title":"star","link":"audio/1b23ea6b-b13b-4cd1-b1f4-ce5210f30408.mp3","name_original":"","voices_id":65,"id":256210,"sync_data":""}],"video":[],"type":"question","order":0},{"path":"fde4585b-dcbd-4651-80a1-541d6d7ee985_358746.zip","image":[],"word_id":40156702,"text":"st","audio":[{"duration":0,"file_path":"ed325299-8a02-48e7-b2b9-76636b97e40f.mp3","score":0,"voices_type_id":65,"tag_title":"st","link":"audio/ed325299-8a02-48e7-b2b9-76636b97e40f.mp3","name_original":"","voices_id":65,"id":256211,"sync_data":""}],"video":[],"type":"phonic","order":0},{"path":"acde2145-9eda-4acd-9720-7251ecb49cae_358747.zip","image":[],"word_id":40156703,"text":"a","audio":[{"duration":0,"file_path":"a6741206-59f3-4bf3-bf80-44e4b5e4d211.mp3","score":0,"voices_type_id":65,"tag_title":"a","link":"audio/a6741206-59f3-4bf3-bf80-44e4b5e4d211.mp3","name_original":"","voices_id":65,"id":256212,"sync_data":""}],"video":[],"type":"phonic","order":0},{"path":"bcf9e242-71dd-419f-b33d-e396c31b395c_358748.zip","image":[],"word_id":40156704,"text":"r","audio":[{"duration":0,"file_path":"6f901e42-f2ad-4c6d-8f9c-bf20a1ad99f7.mp3","score":0,"voices_type_id":65,"tag_title":"r","link":"audio/6f901e42-f2ad-4c6d-8f9c-bf20a1ad99f7.mp3","name_original":"","voices_id":65,"id":256213,"sync_data":""}],"video":[],"type":"phonic","order":0},{"path":"c15807bf-4b2f-4e74-bb7c-faee88906b39_358749.zip","image":[],"word_id":40156705,"text":"st","audio":[{"duration":0,"file_path":"9d8377f0-ae14-4496-9111-6703ddc5fae1.mp3","score":0,"voices_type_id":65,"tag_title":"st","link":"audio/9d8377f0-ae14-4496-9111-6703ddc5fae1.mp3","name_original":"","voices_id":65,"id":256214,"sync_data":""}],"video":[],"type":"phonic","order":0},{"path":"9d1d7b00-3e2e-410a-afcc-ba8c99894ee7_358750.zip","image":[],"word_id":40156706,"text":"ar","audio":[{"duration":0,"file_path":"0dea0cfe-e601-4c0d-9f0f-722df3d4d925.mp3","score":0,"voices_type_id":65,"tag_title":"ar","link":"audio/0dea0cfe-e601-4c0d-9f0f-722df3d4d925.mp3","name_original":"","voices_id":65,"id":256215,"sync_data":""}],"video":[],"type":"phonic","order":0}],"phonic":{},"order":1}],"thumb_start":{}},{"file_zip":"1528438-57771-htn.zip","story_name":{},"thumb_end":{},"background":"","act_id":1528438,"id":1000162,"turn":[{"right_answer":[],"word":[{"path":"7b79edb2-d580-4a52-9707-af26178b424b_358317.zip","image":[],"word_id":40156273,"text":"bone","audio":[{"duration":0,"file_path":"27ffebeb-cc54-4257-8001-dd9927e771d3.mp3","score":0,"voices_type_id":65,"tag_title":"bone","link":"audio/27ffebeb-cc54-4257-8001-dd9927e771d3.mp3","name_original":"","voices_id":65,"id":255790,"sync_data":""}],"video":[],"type":"question","order":0},{"path":"aa64fc1f-0982-47b2-b49e-db05b5fb03df_358318.zip","image":[],"word_id":40156274,"text":"b","audio":[{"duration":0,"file_path":"fd9ac6a6-e2b7-4937-9305-0670bab88ce4.mp3","score":0,"voices_type_id":65,"tag_title":"b","link":"audio/fd9ac6a6-e2b7-4937-9305-0670bab88ce4.mp3","name_original":"","voices_id":65,"id":255791,"sync_data":""}],"video":[],"type":"phonic","order":0},{"path":"78a48a6f-82b3-46ea-818a-959fddb83ec1_358319.zip","image":[],"word_id":40156275,"text":"o_e","audio":[{"duration":0,"file_path":"a0d6e421-2fcb-4dd7-94ce-76d8ed41ed0c.mp3","score":0,"voices_type_id":65,"tag_title":"o_e","link":"audio/a0d6e421-2fcb-4dd7-94ce-76d8ed41ed0c.mp3","name_original":"","voices_id":65,"id":255792,"sync_data":""}],"video":[],"type":"phonic","order":0},{"path":"f93f4a81-89d6-44c8-a90b-3b7dcdf0dc3a_358320.zip","image":[],"word_id":40156276,"text":"n","audio":[{"duration":0,"file_path":"e6015282-6bec-44d7-8538-76c82c1adbaa.mp3","score":0,"voices_type_id":65,"tag_title":"n","link":"audio/e6015282-6bec-44d7-8538-76c82c1adbaa.mp3","name_original":"","voices_id":65,"id":255793,"sync_data":""}],"video":[],"type":"phonic","order":0}],"phonic":{},"order":1}],"thumb_start":{}},{"file_zip":"1528474-57756-tyo.zip","story_name":{},"thumb_end":{},"background":"","act_id":1528474,"id":1000162,"turn":[{"right_answer":[],"word":[{"path":"bfc3e386-6bb1-4ce2-982c-6bdac3d70ef1_358535.zip","image":[],"word_id":40156491,"text":"fume","audio":[{"duration":0,"file_path":"ea0df6a5-3e33-48ed-9d47-a154f2e096ff.mp3","score":0,"voices_type_id":65,"tag_title":"fume","link":"audio/ea0df6a5-3e33-48ed-9d47-a154f2e096ff.mp3","name_original":"","voices_id":65,"id":256002,"sync_data":""}],"video":[],"type":"question","order":0},{"path":"6768b50c-5c61-46d1-a129-2892ebff9962_358536.zip","image":[],"word_id":40156492,"text":"f","audio":[{"duration":0,"file_path":"fc2f1bfb-cc78-4fce-bfc6-290df2c7963a.mp3","score":0,"voices_type_id":65,"tag_title":"f","link":"audio/fc2f1bfb-cc78-4fce-bfc6-290df2c7963a.mp3","name_original":"","voices_id":65,"id":256003,"sync_data":""}],"video":[],"type":"phonic","order":0},{"path":"0b399627-c850-4ee5-80d9-14a6d5ca3fe2_358537.zip","image":[],"word_id":40156493,"text":"u_e","audio":[{"duration":0,"file_path":"5cdf9c28-f935-45ba-9522-459ebc11a742.mp3","score":0,"voices_type_id":65,"tag_title":"u_e","link":"audio/5cdf9c28-f935-45ba-9522-459ebc11a742.mp3","name_original":"","voices_id":65,"id":256004,"sync_data":""}],"video":[],"type":"phonic","order":0},{"path":"96e5c4db-42ca-4bee-952e-ef8ce0e7667c_358538.zip","image":[],"word_id":40156494,"text":"m","audio":[{"duration":0,"file_path":"64667945-309a-4eeb-a471-c656c4ea6d5d.mp3","score":0,"voices_type_id":65,"tag_title":"m","link":"audio/64667945-309a-4eeb-a471-c656c4ea6d5d.mp3","name_original":"","voices_id":65,"id":256005,"sync_data":""}],"video":[],"type":"phonic","order":0}],"phonic":{},"order":1}],"thumb_start":{}},{"file_zip":"1528555-57734-rsu.zip","story_name":{},"thumb_end":{},"background":"","act_id":1528555,"id":1000162,"turn":[{"right_answer":[],"word":[{"path":"b454fe69-1859-4bae-afcf-9834c98d570b_358840.zip","image":[],"word_id":40156796,"text":"yawn","audio":[{"duration":0,"file_path":"cf4b4460-cd5d-4ab7-9888-1f3d2d9a4287.mp3","score":0,"voices_type_id":65,"tag_title":"yawn","link":"audio/cf4b4460-cd5d-4ab7-9888-1f3d2d9a4287.mp3","name_original":"","voices_id":65,"id":256309,"sync_data":""}],"video":[],"type":"question","order":0},{"path":"a6e25578-7037-402a-af4c-6ede3b81aac7_358841.zip","image":[],"word_id":40156797,"text":"y","audio":[{"duration":0,"file_path":"da837620-2f9f-4655-8106-8fbc2e2a415b.mp3","score":0,"voices_type_id":65,"tag_title":"y","link":"audio/da837620-2f9f-4655-8106-8fbc2e2a415b.mp3","name_original":"","voices_id":65,"id":256310,"sync_data":""}],"video":[],"type":"phonic","order":0},{"path":"92ad8041-f8ef-431f-8cc2-8e0038d36b67_358842.zip","image":[],"word_id":40156798,"text":"aw","audio":[{"duration":0,"file_path":"9d8e7eba-5126-4794-a83d-20dc0722ff2d.mp3","score":0,"voices_type_id":65,"tag_title":"aw","link":"audio/9d8e7eba-5126-4794-a83d-20dc0722ff2d.mp3","name_original":"","voices_id":65,"id":256311,"sync_data":""}],"video":[],"type":"phonic","order":0},{"path":"c6dc597e-f529-47f9-ae26-ec0830ca0139_358843.zip","image":[],"word_id":40156799,"text":"n","audio":[{"duration":0,"file_path":"cf238c90-fdf0-4f3b-944d-2463916be5f5.mp3","score":0,"voices_type_id":65,"tag_title":"n","link":"audio/cf238c90-fdf0-4f3b-944d-2463916be5f5.mp3","name_original":"","voices_id":65,"id":256312,"sync_data":""}],"video":[],"type":"phonic","order":0}],"phonic":{},"order":1}],"thumb_start":{}},{"file_zip":"1528573-57763-bbi.zip","story_name":{},"thumb_end":{},"background":"","act_id":1528573,"id":1000162,"turn":[{"right_answer":[],"word":[{"path":"58151b28-671b-4a4a-bada-b696a6132fde_358412.zip","image":[],"word_id":40156368,"text":"five","audio":[{"duration":0,"file_path":"a4074a27-a1ce-4bc3-b4fe-f41277bc9263.mp3","score":0,"voices_type_id":65,"tag_title":"five","link":"audio/a4074a27-a1ce-4bc3-b4fe-f41277bc9263.mp3","name_original":"","voices_id":65,"id":255887,"sync_data":""}],"video":[],"type":"question","order":0},{"path":"9e9f00a7-495a-4c09-b519-40db79bf99ed_358413.zip","image":[],"word_id":40156369,"text":"f","audio":[{"duration":0,"file_path":"b579ec73-48ac-4415-b737-43510b202404.mp3","score":0,"voices_type_id":65,"tag_title":"f","link":"audio/b579ec73-48ac-4415-b737-43510b202404.mp3","name_original":"","voices_id":65,"id":255888,"sync_data":""}],"video":[],"type":"phonic","order":0},{"path":"af4c27a9-f6fb-4392-aecd-25098c133375_358414.zip","image":[],"word_id":40156370,"text":"i_e","audio":[{"duration":0,"file_path":"95b40b4f-757a-40ed-a436-03fb0f4fd04b.mp3","score":0,"voices_type_id":65,"tag_title":"i_e","link":"audio/95b40b4f-757a-40ed-a436-03fb0f4fd04b.mp3","name_original":"","voices_id":65,"id":255889,"sync_data":""}],"video":[],"type":"phonic","order":0},{"path":"58d63890-b1df-4a09-a9db-64959e563d9a_358415.zip","image":[],"word_id":40156371,"text":"v","audio":[{"duration":0,"file_path":"12e8c9ad-413a-4f4e-aaa6-99bc617ff761.mp3","score":0,"voices_type_id":65,"tag_title":"v","link":"audio/12e8c9ad-413a-4f4e-aaa6-99bc617ff761.mp3","name_original":"","voices_id":65,"id":255890,"sync_data":""}],"video":[],"type":"phonic","order":0}],"phonic":{},"order":1}],"thumb_start":{}},{"file_zip":"1528606-57748-lvu.zip","story_name":{},"thumb_end":{},"background":"","act_id":1528606,"id":1000162,"turn":[{"right_answer":[],"word":[{"path":"8ad761a1-67b7-4492-b20f-b7b3ce0ef23c_358625.zip","image":[],"word_id":40156581,"text":"meme","audio":[{"duration":0,"file_path":"a5f7e77b-81a2-4e74-bf64-f6664a9bd25f.mp3","score":0,"voices_type_id":65,"tag_title":"meme","link":"audio/a5f7e77b-81a2-4e74-bf64-f6664a9bd25f.mp3","name_original":"","voices_id":65,"id":256096,"sync_data":""}],"video":[],"type":"question","order":0},{"path":"51a93355-6255-403b-966e-6d5ffe99b50e_358626.zip","image":[],"word_id":40156582,"text":"m","audio":[{"duration":0,"file_path":"680af780-2e56-4ad6-9f80-9fed1df23183.mp3","score":0,"voices_type_id":65,"tag_title":"m","link":"audio/680af780-2e56-4ad6-9f80-9fed1df23183.mp3","name_original":"","voices_id":65,"id":256097,"sync_data":""}],"video":[],"type":"phonic","order":0},{"path":"a477c547-f510-427d-ac43-4b88a8c483d3_358627.zip","image":[],"word_id":40156583,"text":"e_e","audio":[{"duration":0,"file_path":"6e1542f6-6f7c-47c7-97e9-a84ce81f583b.mp3","score":0,"voices_type_id":65,"tag_title":"e_e","link":"audio/6e1542f6-6f7c-47c7-97e9-a84ce81f583b.mp3","name_original":"","voices_id":65,"id":256098,"sync_data":""}],"video":[],"type":"phonic","order":0},{"path":"39890556-bec4-4e08-8a44-45631102ab74_358628.zip","image":[],"word_id":40156584,"text":"m","audio":[{"duration":0,"file_path":"b3078949-3e22-4291-8645-4bfe09a84adc.mp3","score":0,"voices_type_id":65,"tag_title":"m","link":"audio/b3078949-3e22-4291-8645-4bfe09a84adc.mp3","name_original":"","voices_id":65,"id":256099,"sync_data":""}],"video":[],"type":"phonic","order":0}],"phonic":{},"order":1}],"thumb_start":{}},{"file_zip":"1528631-57786-hmx.zip","story_name":{},"thumb_end":{},"background":"","act_id":1528631,"id":1000162,"turn":[{"right_answer":[],"word":[{"path":"3939955a-ed50-48d6-b62d-aabbbbee8764_358107.zip","image":[],"word_id":40156063,"text":"smog","audio":[{"duration":0,"file_path":"fb366652-94cb-4578-990e-483e174d7cad.mp3","score":0,"voices_type_id":65,"tag_title":"smog","link":"audio/fb366652-94cb-4578-990e-483e174d7cad.mp3","name_original":"","voices_id":65,"id":255584,"sync_data":""}],"video":[],"type":"question","order":0},{"path":"b6ff37d9-8e1e-4570-b742-a583907a7a88_358108.zip","image":[],"word_id":40156064,"text":"sm","audio":[{"duration":0,"file_path":"137e4577-9832-43b9-bbd2-69a98ea392c6.mp3","score":0,"voices_type_id":65,"tag_title":"sm","link":"audio/137e4577-9832-43b9-bbd2-69a98ea392c6.mp3","name_original":"","voices_id":65,"id":255585,"sync_data":""}],"video":[],"type":"phonic","order":0},{"path":"b3a810a7-c7e7-4cbd-a838-4f451fbb6cb9_358109.zip","image":[],"word_id":40156065,"text":"o","audio":[{"duration":0,"file_path":"3e166a77-5766-4de0-bae3-3751bfdb207f.mp3","score":0,"voices_type_id":65,"tag_title":"o","link":"audio/3e166a77-5766-4de0-bae3-3751bfdb207f.mp3","name_original":"","voices_id":65,"id":255586,"sync_data":""}],"video":[],"type":"phonic","order":0},{"path":"28658d36-2284-4761-882d-7e37d8f953d1_358110.zip","image":[],"word_id":40156066,"text":"g","audio":[{"duration":0,"file_path":"aa5be9e7-d0b2-4b6b-bd61-d9cf4f06cb8e.mp3","score":0,"voices_type_id":65,"tag_title":"g","link":"audio/aa5be9e7-d0b2-4b6b-bd61-d9cf4f06cb8e.mp3","name_original":"","voices_id":65,"id":255587,"sync_data":""}],"video":[],"type":"phonic","order":0}],"phonic":{},"order":1}],"thumb_start":{}},{"file_zip":"1528652-57801-atf.zip","story_name":{},"thumb_end":{},"background":"","act_id":1528652,"id":1000162,"turn":[{"right_answer":[],"word":[{"path":"48b8c28f-6208-4765-b430-a7f873672cd4_357885.zip","image":[],"word_id":40155841,"text":"flag","audio":[{"duration":0,"file_path":"85e5bdcd-4457-449f-b0b6-82a8a6811bfa.mp3","score":0,"voices_type_id":65,"tag_title":"flag","link":"audio/85e5bdcd-4457-449f-b0b6-82a8a6811bfa.mp3","name_original":"","voices_id":65,"id":255366,"sync_data":""}],"video":[],"type":"question","order":0},{"path":"7711f1fb-eb73-4aa2-94c3-882f5bb6f9b3_357886.zip","image":[],"word_id":40155842,"text":"fl","audio":[{"duration":0,"file_path":"8d370a0c-0933-48b2-9aeb-935ea9e9c4ff.mp3","score":0,"voices_type_id":65,"tag_title":"fl","link":"audio/8d370a0c-0933-48b2-9aeb-935ea9e9c4ff.mp3","name_original":"","voices_id":65,"id":255367,"sync_data":""}],"video":[],"type":"phonic","order":0},{"path":"8857bfb5-8f88-4287-9f6c-7fd0dfb8f0ea_357887.zip","image":[],"word_id":40155843,"text":"a","audio":[{"duration":0,"file_path":"06839ab4-e51a-497c-9e23-8e33d80df853.mp3","score":0,"voices_type_id":65,"tag_title":"a","link":"audio/06839ab4-e51a-497c-9e23-8e33d80df853.mp3","name_original":"","voices_id":65,"id":255368,"sync_data":""}],"video":[],"type":"phonic","order":0},{"path":"36a520a7-e133-4aeb-9d9a-4b2e6ecccfa5_357888.zip","image":[],"word_id":40155844,"text":"g","audio":[{"duration":0,"file_path":"2cdf2128-de02-4c95-8965-a5cff491593d.mp3","score":0,"voices_type_id":65,"tag_title":"g","link":"audio/2cdf2128-de02-4c95-8965-a5cff491593d.mp3","name_original":"","voices_id":65,"id":255369,"sync_data":""}],"video":[],"type":"phonic","order":0}],"phonic":{},"order":1}],"thumb_start":{}},{"file_zip":"1528718-57713-arq.zip","story_name":{},"thumb_end":{},"background":"","act_id":1528718,"id":1000162,"turn":[{"right_answer":[],"word":[{"path":"29b56b2c-0099-4fbf-8bde-f5a997f8693a_359172.zip","image":[],"word_id":40157128,"text":"dew","audio":[{"duration":0,"file_path":"ba431baa-5247-41d1-8e20-a00846e6d4f4.mp3","score":0,"voices_type_id":65,"tag_title":"dew","link":"audio/ba431baa-5247-41d1-8e20-a00846e6d4f4.mp3","name_original":"","voices_id":65,"id":256634,"sync_data":""}],"video":[],"type":"question","order":0},{"path":"8cdeb70e-ac9f-48d5-a06d-c1631e241322_359173.zip","image":[],"word_id":40157129,"text":"d","audio":[{"duration":0,"file_path":"676ed0b5-3edc-4b68-be28-d540a6f48dda.mp3","score":0,"voices_type_id":65,"tag_title":"d","link":"audio/676ed0b5-3edc-4b68-be28-d540a6f48dda.mp3","name_original":"","voices_id":65,"id":256635,"sync_data":""}],"video":[],"type":"phonic","order":0},{"path":"3f95f8fc-f43f-4951-ad9f-70c3ba935ac1_359174.zip","image":[],"word_id":40157130,"text":"ew","audio":[{"duration":0,"file_path":"4c48b3bf-14e0-4bf9-b314-765914e2346b.mp3","score":0,"voices_type_id":65,"tag_title":"ew","link":"audio/4c48b3bf-14e0-4bf9-b314-765914e2346b.mp3","name_original":"","voices_id":65,"id":256636,"sync_data":""}],"video":[],"type":"phonic","order":0}],"phonic":{},"order":1}],"thumb_start":{}},{"file_zip":"1528744-57691-knr.zip","story_name":{},"thumb_end":{},"background":"","act_id":1528744,"id":1000162,"turn":[{"right_answer":[],"word":[{"path":"9079e756-af41-41b7-a278-6de3694fd72b_359477.zip","image":[],"word_id":40157433,"text":"turn","audio":[{"duration":0,"file_path":"555a0d52-f499-4092-8571-0640d1e32492.mp3","score":0,"voices_type_id":65,"tag_title":"turn","link":"audio/555a0d52-f499-4092-8571-0640d1e32492.mp3","name_original":"","voices_id":65,"id":256939,"sync_data":""}],"video":[],"type":"question","order":0},{"path":"8d035680-12d9-4585-86f6-7c383be4c42b_359478.zip","image":[],"word_id":40157434,"text":"t","audio":[{"duration":0,"file_path":"6db44a1f-bf84-459f-97dd-352add19028a.mp3","score":0,"voices_type_id":65,"tag_title":"t","link":"audio/6db44a1f-bf84-459f-97dd-352add19028a.mp3","name_original":"","voices_id":65,"id":256940,"sync_data":""}],"video":[],"type":"phonic","order":0},{"path":"0c0bb273-8fd0-4672-ba22-3982f87759ae_359479.zip","image":[],"word_id":40157435,"text":"ur","audio":[{"duration":0,"file_path":"dbb394f4-8c0e-4e37-9a16-a50156773ea7.mp3","score":0,"voices_type_id":65,"tag_title":"ur","link":"audio/dbb394f4-8c0e-4e37-9a16-a50156773ea7.mp3","name_original":"","voices_id":65,"id":256941,"sync_data":""}],"video":[],"type":"phonic","order":0},{"path":"366083c9-7624-446e-8f0d-9182a691cf85_359480.zip","image":[],"word_id":40157436,"text":"n","audio":[{"duration":0,"file_path":"9579d306-2ef8-448d-a6ed-73ecf881cc60.mp3","score":0,"voices_type_id":65,"tag_title":"n","link":"audio/9579d306-2ef8-448d-a6ed-73ecf881cc60.mp3","name_original":"","voices_id":65,"id":256942,"sync_data":""}],"video":[],"type":"phonic","order":0}],"phonic":{},"order":1}],"thumb_start":{}},{"file_zip":"1528762-57706-frr.zip","story_name":{},"thumb_end":{},"background":"","act_id":1528762,"id":1000162,"turn":[{"right_answer":[],"word":[{"path":"285c43e6-1317-44a2-956b-b11a352ad309_359265.zip","image":[],"word_id":40157221,"text":"river","audio":[{"duration":0,"file_path":"8936d39f-e580-4d95-8056-6c4c9ddaf94d.mp3","score":0,"voices_type_id":65,"tag_title":"river","link":"audio/8936d39f-e580-4d95-8056-6c4c9ddaf94d.mp3","name_original":"","voices_id":65,"id":256731,"sync_data":""}],"video":[],"type":"question","order":0},{"path":"f07685dc-8a9b-48dd-bd73-91e73bf31903_359266.zip","image":[],"word_id":40157222,"text":"r","audio":[{"duration":0,"file_path":"8789306c-a8c1-4fb7-8731-55b1f7c50123.mp3","score":0,"voices_type_id":65,"tag_title":"r","link":"audio/8789306c-a8c1-4fb7-8731-55b1f7c50123.mp3","name_original":"","voices_id":65,"id":256732,"sync_data":""}],"video":[],"type":"phonic","order":0},{"path":"6c7532b7-c752-4b43-96ee-08605896f9f7_359267.zip","image":[],"word_id":40157223,"text":"i","audio":[{"duration":0,"file_path":"30a90261-4473-4383-90cc-88b2683e5d22.mp3","score":0,"voices_type_id":65,"tag_title":"i","link":"audio/30a90261-4473-4383-90cc-88b2683e5d22.mp3","name_original":"","voices_id":65,"id":256733,"sync_data":""}],"video":[],"type":"phonic","order":0},{"path":"b2a4b73f-df03-47c5-9854-c060ad621f1c_359268.zip","image":[],"word_id":40157224,"text":"v","audio":[{"duration":0,"file_path":"e7ee83af-4451-4d49-b1ad-97f1215d76a8.mp3","score":0,"voices_type_id":65,"tag_title":"v","link":"audio/e7ee83af-4451-4d49-b1ad-97f1215d76a8.mp3","name_original":"","voices_id":65,"id":256734,"sync_data":""}],"video":[],"type":"phonic","order":0},{"path":"c02f3f33-1fcc-4453-a13b-95bd4e063a5a_359269.zip","image":[],"word_id":40157225,"text":"er","audio":[{"duration":0,"file_path":"1be69156-d604-4940-9f3a-b9be819bf86c.mp3","score":0,"voices_type_id":65,"tag_title":"er","link":"audio/1be69156-d604-4940-9f3a-b9be819bf86c.mp3","name_original":"","voices_id":65,"id":256735,"sync_data":""}],"video":[],"type":"phonic","order":0}],"phonic":{},"order":1}],"thumb_start":{}},{"file_zip":"1528789-57720-aiv.zip","story_name":{},"thumb_end":{},"background":"","act_id":1528789,"id":1000162,"turn":[{"right_answer":[],"word":[{"path":"b4421ffb-8dfb-44ae-893d-bfe4cf368031_359049.zip","image":[],"word_id":40157005,"text":"trolley","audio":[{"duration":0,"file_path":"0fb69da4-08d7-470c-8e87-67a2d7e62303.mp3","score":0,"voices_type_id":65,"tag_title":"trolley","link":"audio/0fb69da4-08d7-470c-8e87-67a2d7e62303.mp3","name_original":"","voices_id":65,"id":256517,"sync_data":""}],"video":[],"type":"question","order":0},{"path":"3279cf5b-892b-4cf2-9d51-44c0686d4840_359050.zip","image":[],"word_id":40157006,"text":"tr","audio":[{"duration":0,"file_path":"c85dffd1-aec0-41e0-99aa-3bf6a3cedc2b.mp3","score":0,"voices_type_id":65,"tag_title":"tr","link":"audio/c85dffd1-aec0-41e0-99aa-3bf6a3cedc2b.mp3","name_original":"","voices_id":65,"id":256518,"sync_data":""}],"video":[],"type":"phonic","order":0},{"path":"be4d978c-222c-4887-8ab3-ccf1adc5663a_359051.zip","image":[],"word_id":40157007,"text":"o","audio":[{"duration":0,"file_path":"af7ef38f-2460-436c-a48e-8ea2c260a307.mp3","score":0,"voices_type_id":65,"tag_title":"o","link":"audio/af7ef38f-2460-436c-a48e-8ea2c260a307.mp3","name_original":"","voices_id":65,"id":256519,"sync_data":""}],"video":[],"type":"phonic","order":0},{"path":"7d45afd4-d2c5-4456-9e49-22edc63e26de_359052.zip","image":[],"word_id":40157008,"text":"ll","audio":[{"duration":0,"file_path":"acfa13ef-d3a5-48c5-9bde-2b200046d9ec.mp3","score":0,"voices_type_id":65,"tag_title":"ll","link":"audio/acfa13ef-d3a5-48c5-9bde-2b200046d9ec.mp3","name_original":"","voices_id":65,"id":256520,"sync_data":""}],"video":[],"type":"phonic","order":0},{"path":"94adf264-5f65-4031-89bc-98c3751af563_359053.zip","image":[],"word_id":40157009,"text":"ey","audio":[{"duration":0,"file_path":"6504cb82-41e3-43d5-b87a-75324e71ef8f.mp3","score":0,"voices_type_id":65,"tag_title":"ey","link":"audio/6504cb82-41e3-43d5-b87a-75324e71ef8f.mp3","name_original":"","voices_id":65,"id":256521,"sync_data":""}],"video":[],"type":"phonic","order":0}],"phonic":{},"order":1}],"thumb_start":{}},{"file_zip":"1528798-57661-pbo.zip","story_name":{},"thumb_end":{},"background":"","act_id":1528798,"id":1000162,"turn":[{"right_answer":[],"word":[{"path":"c6ff10a8-aed8-4293-9e52-5685763720ba_359912.zip","image":[],"word_id":40157868,"text":"pink","audio":[{"duration":0,"file_path":"c8f7d6a4-07f2-4b8f-b30d-4d9816bc50b8.mp3","score":0,"voices_type_id":65,"tag_title":"pink","link":"audio/c8f7d6a4-07f2-4b8f-b30d-4d9816bc50b8.mp3","name_original":"","voices_id":65,"id":257363,"sync_data":""}],"video":[],"type":"question","order":0},{"path":"397059f8-c5ad-498d-87a3-f0e23248f7fe_359913.zip","image":[],"word_id":40157869,"text":"p","audio":[{"duration":0,"file_path":"c94f46b1-e60e-43e0-87db-716602974688.mp3","score":0,"voices_type_id":65,"tag_title":"p","link":"audio/c94f46b1-e60e-43e0-87db-716602974688.mp3","name_original":"","voices_id":65,"id":257364,"sync_data":""}],"video":[],"type":"phonic","order":0},{"path":"ea9f459c-6d9d-4466-a41c-a2f6b48a1995_359914.zip","image":[],"word_id":40157870,"text":"i","audio":[{"duration":0,"file_path":"0230be16-26cb-4838-99f3-a0055e3ca7c6.mp3","score":0,"voices_type_id":65,"tag_title":"i","link":"audio/0230be16-26cb-4838-99f3-a0055e3ca7c6.mp3","name_original":"","voices_id":65,"id":257365,"sync_data":""}],"video":[],"type":"phonic","order":0},{"path":"9f9c25c3-13d0-4fa5-af98-2f0ca2c5ce40_359915.zip","image":[],"word_id":40157871,"text":"nk","audio":[{"duration":0,"file_path":"257a30eb-0ed2-4460-b412-51606af54587.mp3","score":0,"voices_type_id":65,"tag_title":"nk","link":"audio/257a30eb-0ed2-4460-b412-51606af54587.mp3","name_original":"","voices_id":65,"id":257366,"sync_data":""}],"video":[],"type":"phonic","order":0}],"phonic":{},"order":1}],"thumb_start":{}},{"file_zip":"1528807-57728-xov.zip","story_name":{},"thumb_end":{},"background":"","act_id":1528807,"id":1000162,"turn":[{"right_answer":[],"word":[{"path":"c38a6e25-6df1-4d30-b4d8-a9f4695d9bae_358960.zip","image":[],"word_id":40156916,"text":"vein","audio":[{"duration":0,"file_path":"618d4003-6b73-4f40-adfb-f764928abd66.mp3","score":0,"voices_type_id":65,"tag_title":"vein","link":"audio/618d4003-6b73-4f40-adfb-f764928abd66.mp3","name_original":"","voices_id":65,"id":256422,"sync_data":""}],"video":[],"type":"question","order":0},{"path":"f13ef4fb-e339-47e8-a3b4-6d5b1b658d82_358961.zip","image":[],"word_id":40156917,"text":"v","audio":[{"duration":0,"file_path":"fda8862e-f7c7-40ef-83d4-02e6a5a5f14f.mp3","score":0,"voices_type_id":65,"tag_title":"v","link":"audio/fda8862e-f7c7-40ef-83d4-02e6a5a5f14f.mp3","name_original":"","voices_id":65,"id":256423,"sync_data":""}],"video":[],"type":"phonic","order":0},{"path":"8ef9473c-3913-4b51-afd6-586d5375cad8_358962.zip","image":[],"word_id":40156918,"text":"ei","audio":[{"duration":0,"file_path":"7d7a44c5-3e79-48bb-9bda-62f11183d6bd.mp3","score":0,"voices_type_id":65,"tag_title":"ei","link":"audio/7d7a44c5-3e79-48bb-9bda-62f11183d6bd.mp3","name_original":"","voices_id":65,"id":256424,"sync_data":""}],"video":[],"type":"phonic","order":0},{"path":"ee2ac60b-9067-40cd-8fbe-aa02d0b79931_358963.zip","image":[],"word_id":40156919,"text":"n","audio":[{"duration":0,"file_path":"31540bfa-79b8-409b-8cc8-06c49522b5ff.mp3","score":0,"voices_type_id":65,"tag_title":"n","link":"audio/31540bfa-79b8-409b-8cc8-06c49522b5ff.mp3","name_original":"","voices_id":65,"id":256425,"sync_data":""}],"video":[],"type":"phonic","order":0}],"phonic":{},"order":1}],"thumb_start":{}},{"file_zip":"1528822-57676-qme.zip","story_name":{},"thumb_end":{},"background":"","act_id":1528822,"id":1000162,"turn":[{"right_answer":[],"word":[{"path":"cfc1c91d-2c71-422b-b981-92c5fc28e6f5_359696.zip","image":[],"word_id":40157652,"text":"bend","audio":[{"duration":0,"file_path":"ff916333-5cf2-4a2f-9702-7ec72f2d33d5.mp3","score":0,"voices_type_id":65,"tag_title":"bend","link":"audio/ff916333-5cf2-4a2f-9702-7ec72f2d33d5.mp3","name_original":"","voices_id":65,"id":257153,"sync_data":""}],"video":[],"type":"question","order":0},{"path":"27c973c6-d8de-4534-a498-830aa25d2c41_359697.zip","image":[],"word_id":40157653,"text":"b","audio":[{"duration":0,"file_path":"bcc243ea-30c0-4ebd-80fa-eb66e3c03088.mp3","score":0,"voices_type_id":65,"tag_title":"b","link":"audio/bcc243ea-30c0-4ebd-80fa-eb66e3c03088.mp3","name_original":"","voices_id":65,"id":257154,"sync_data":""}],"video":[],"type":"phonic","order":0},{"path":"9809b1ae-0be9-4d79-8ecc-6c2d0bc933c7_359698.zip","image":[],"word_id":40157654,"text":"e","audio":[{"duration":0,"file_path":"9430d556-7276-41ff-9a6d-125945e3f081.mp3","score":0,"voices_type_id":65,"tag_title":"e","link":"audio/9430d556-7276-41ff-9a6d-125945e3f081.mp3","name_original":"","voices_id":65,"id":257155,"sync_data":""}],"video":[],"type":"phonic","order":0},{"path":"ad604bc5-b3ad-47f9-8ff2-a6c169f7a63b_359699.zip","image":[],"word_id":40157655,"text":"nd","audio":[{"duration":0,"file_path":"303f0162-15cc-4857-a359-b54647c95dd6.mp3","score":0,"voices_type_id":65,"tag_title":"nd","link":"audio/303f0162-15cc-4857-a359-b54647c95dd6.mp3","name_original":"","voices_id":65,"id":257156,"sync_data":""}],"video":[],"type":"phonic","order":0}],"phonic":{},"order":1}],"thumb_start":{}},{"file_zip":"1528844-57699-dop.zip","story_name":{},"thumb_end":{},"background":"","act_id":1528844,"id":1000162,"turn":[{"right_answer":[],"word":[{"path":"aed9963c-aaef-43c5-80cb-995277f9138a_359387.zip","image":[],"word_id":40157343,"text":"stir","audio":[{"duration":0,"file_path":"13d00da5-34b9-4e5e-906a-3fd5a5b51993.mp3","score":0,"voices_type_id":65,"tag_title":"stir","link":"audio/13d00da5-34b9-4e5e-906a-3fd5a5b51993.mp3","name_original":"","voices_id":65,"id":256845,"sync_data":""}],"video":[],"type":"question","order":0},{"path":"8606635b-5583-4da9-b859-2220b5ed43c6_359388.zip","image":[],"word_id":40157344,"text":"st","audio":[{"duration":0,"file_path":"91e4e3b9-38b1-49c6-ae99-bd280aa288e0.mp3","score":0,"voices_type_id":65,"tag_title":"st","link":"audio/91e4e3b9-38b1-49c6-ae99-bd280aa288e0.mp3","name_original":"","voices_id":65,"id":256846,"sync_data":""}],"video":[],"type":"phonic","order":0},{"path":"345d881c-6802-41bc-a296-7528e8ff990b_359389.zip","image":[],"word_id":40157345,"text":"ir","audio":[{"duration":0,"file_path":"dea9eb9d-640e-4bb4-9fa9-205a2ef23d00.mp3","score":0,"voices_type_id":65,"tag_title":"ir","link":"audio/dea9eb9d-640e-4bb4-9fa9-205a2ef23d00.mp3","name_original":"","voices_id":65,"id":256847,"sync_data":""}],"video":[],"type":"phonic","order":0}],"phonic":{},"order":1}],"thumb_start":{}},{"file_zip":"1528849-57684-ivi.zip","story_name":{},"thumb_end":{},"background":"","act_id":1528849,"id":1000162,"turn":[{"right_answer":[],"word":[{"path":"d5333ee6-fcbc-410e-80d8-b730d72f5969_359602.zip","image":[],"word_id":40157558,"text":"port","audio":[{"duration":0,"file_path":"07a04650-a259-411e-9fe4-d453a519d666.mp3","score":0,"voices_type_id":65,"tag_title":"port","link":"audio/07a04650-a259-411e-9fe4-d453a519d666.mp3","name_original":"","voices_id":65,"id":257055,"sync_data":""}],"video":[],"type":"question","order":0},{"path":"b2d42b9b-3708-4ac4-9340-b9238c8a761f_359603.zip","image":[],"word_id":40157559,"text":"p","audio":[{"duration":0,"file_path":"074d214d-1cd6-4800-88f7-3ebaf12298ea.mp3","score":0,"voices_type_id":65,"tag_title":"p","link":"audio/074d214d-1cd6-4800-88f7-3ebaf12298ea.mp3","name_original":"","voices_id":65,"id":257056,"sync_data":""}],"video":[],"type":"phonic","order":0},{"path":"f03569ef-13bb-4f4a-9eb5-fc885ee0b2e1_359604.zip","image":[],"word_id":40157560,"text":"or","audio":[{"duration":0,"file_path":"0e7d21da-8dec-419a-aff1-09e9f5e33959.mp3","score":0,"voices_type_id":65,"tag_title":"or","link":"audio/0e7d21da-8dec-419a-aff1-09e9f5e33959.mp3","name_original":"","voices_id":65,"id":257057,"sync_data":""}],"video":[],"type":"phonic","order":0},{"path":"acbd011e-d39c-4d33-90ca-8deb483883c2_359605.zip","image":[],"word_id":40157561,"text":"t","audio":[{"duration":0,"file_path":"3c3649c4-6d2b-4725-a22b-62a290d1545c.mp3","score":0,"voices_type_id":65,"tag_title":"t","link":"audio/3c3649c4-6d2b-4725-a22b-62a290d1545c.mp3","name_original":"","voices_id":65,"id":257058,"sync_data":""}],"video":[],"type":"phonic","order":0}],"phonic":{},"order":1}],"thumb_start":{}},{"file_zip":"1528928-57669-efx.zip","story_name":{},"thumb_end":{},"background":"","act_id":1528928,"id":1000162,"turn":[{"right_answer":[],"word":[{"path":"cfe669d7-f5f0-4533-b7ce-ba5bb528836a_359815.zip","image":[],"word_id":40157771,"text":"mint","audio":[{"duration":0,"file_path":"0913922a-84fc-40da-9107-c0c9a82e11c9.mp3","score":0,"voices_type_id":65,"tag_title":"mint","link":"audio/0913922a-84fc-40da-9107-c0c9a82e11c9.mp3","name_original":"","voices_id":65,"id":257264,"sync_data":""}],"video":[],"type":"question","order":0},{"path":"f0e7bd6a-d5a9-4005-9e02-1079cf6657b0_359816.zip","image":[],"word_id":40157772,"text":"m","audio":[{"duration":0,"file_path":"ba453533-149d-466a-855e-54f4f6d6dcc3.mp3","score":0,"voices_type_id":65,"tag_title":"m","link":"audio/ba453533-149d-466a-855e-54f4f6d6dcc3.mp3","name_original":"","voices_id":65,"id":257265,"sync_data":""}],"video":[],"type":"phonic","order":0},{"path":"b31c803e-6f0a-4675-a363-f4a642974e21_359817.zip","image":[],"word_id":40157773,"text":"i","audio":[{"duration":0,"file_path":"ccf39a9c-5647-40da-8a9b-1e8c2e697166.mp3","score":0,"voices_type_id":65,"tag_title":"i","link":"audio/ccf39a9c-5647-40da-8a9b-1e8c2e697166.mp3","name_original":"","voices_id":65,"id":257266,"sync_data":""}],"video":[],"type":"phonic","order":0},{"path":"b9d6e5d2-e577-4ac6-a562-bcc10c9adc71_359818.zip","image":[],"word_id":40157774,"text":"nt","audio":[{"duration":0,"file_path":"25de6987-9aff-4168-a2df-c08fbef44a33.mp3","score":0,"voices_type_id":65,"tag_title":"nt","link":"audio/25de6987-9aff-4168-a2df-c08fbef44a33.mp3","name_original":"","voices_id":65,"id":257267,"sync_data":""}],"video":[],"type":"phonic","order":0}],"phonic":{},"order":1}],"thumb_start":{}},{"file_zip":"1529036-57639-dqe.zip","story_name":{},"thumb_end":{},"background":"","act_id":1529036,"id":1000162,"turn":[{"right_answer":[],"word":[{"path":"8e26cb6e-0591-480a-8f75-e0c3f25639d9_360239.zip","image":[],"word_id":40158195,"text":"skip","audio":[{"duration":0,"file_path":"f29d61ee-d50c-41d9-b55c-01a12cf69be8.mp3","score":0,"voices_type_id":65,"tag_title":"skip","link":"audio/f29d61ee-d50c-41d9-b55c-01a12cf69be8.mp3","name_original":"","voices_id":65,"id":257677,"sync_data":""}],"video":[],"type":"question","order":0},{"path":"162e042b-3447-41b1-a3d1-8c01a3bd320b_360240.zip","image":[],"word_id":40158196,"text":"sk","audio":[{"duration":0,"file_path":"5ffd9195-4967-45cc-ab78-3acf7c9de25d.mp3","score":0,"voices_type_id":65,"tag_title":"sk","link":"audio/5ffd9195-4967-45cc-ab78-3acf7c9de25d.mp3","name_original":"","voices_id":65,"id":257678,"sync_data":""}],"video":[],"type":"phonic","order":0},{"path":"03878f72-4a9e-4a12-a0cb-9c60fbde21bb_360241.zip","image":[],"word_id":40158197,"text":"i","audio":[{"duration":0,"file_path":"2e6d1feb-5f62-4830-a997-306fc791feda.mp3","score":0,"voices_type_id":65,"tag_title":"i","link":"audio/2e6d1feb-5f62-4830-a997-306fc791feda.mp3","name_original":"","voices_id":65,"id":257679,"sync_data":""}],"video":[],"type":"phonic","order":0},{"path":"1dac74a4-3114-4948-8af9-3760cc96ded8_360242.zip","image":[],"word_id":40158198,"text":"p","audio":[{"duration":0,"file_path":"55fcefb3-ccdf-46ac-8b99-5c3832d1d814.mp3","score":0,"voices_type_id":65,"tag_title":"p","link":"audio/55fcefb3-ccdf-46ac-8b99-5c3832d1d814.mp3","name_original":"","voices_id":65,"id":257680,"sync_data":""}],"video":[],"type":"phonic","order":0}],"phonic":{},"order":1}],"thumb_start":{}},{"file_zip":"1529123-57624-lxf.zip","story_name":{},"thumb_end":{},"background":"","act_id":1529123,"id":1000162,"turn":[{"right_answer":[],"word":[{"path":"d2f4bcb3-5d4c-4e66-82ac-8f4ffaf4f2f8_360453.zip","image":[],"word_id":40158409,"text":"gulf","audio":[{"duration":0,"file_path":"3f8865f4-0ded-4554-803b-cb0fabff60f9.mp3","score":0,"voices_type_id":65,"tag_title":"gulf","link":"audio/3f8865f4-0ded-4554-803b-cb0fabff60f9.mp3","name_original":"","voices_id":65,"id":257887,"sync_data":""}],"video":[],"type":"question","order":0},{"path":"b0c5b38a-cfa8-4523-a952-76c301c8268f_360454.zip","image":[],"word_id":40158410,"text":"g","audio":[{"duration":0,"file_path":"f67b8898-9d78-4d70-b469-5b1c04adccc1.mp3","score":0,"voices_type_id":65,"tag_title":"g","link":"audio/f67b8898-9d78-4d70-b469-5b1c04adccc1.mp3","name_original":"","voices_id":65,"id":257888,"sync_data":""}],"video":[],"type":"phonic","order":0},{"path":"67cd120a-32ca-4979-8fe7-165af48b655c_360455.zip","image":[],"word_id":40158411,"text":"u","audio":[{"duration":0,"file_path":"a43cdbc4-fa0e-4bdb-85b1-63df74698d4b.mp3","score":0,"voices_type_id":65,"tag_title":"u","link":"audio/a43cdbc4-fa0e-4bdb-85b1-63df74698d4b.mp3","name_original":"","voices_id":65,"id":257889,"sync_data":""}],"video":[],"type":"phonic","order":0},{"path":"a6a1f328-2364-4f40-a53a-73c92827c39f_360456.zip","image":[],"word_id":40158412,"text":"lf","audio":[{"duration":0,"file_path":"6492cbf7-13e2-44e1-9e8b-c07829502555.mp3","score":0,"voices_type_id":65,"tag_title":"lf","link":"audio/6492cbf7-13e2-44e1-9e8b-c07829502555.mp3","name_original":"","voices_id":65,"id":257890,"sync_data":""}],"video":[],"type":"phonic","order":0}],"phonic":{},"order":1}],"thumb_start":{}},{"file_zip":"1529189-57594-lqo.zip","story_name":{},"thumb_end":{},"background":"","act_id":1529189,"id":1000162,"turn":[{"right_answer":[],"word":[{"path":"501f7b18-9ace-4c8a-a2c3-b6ee35fa9fa3_360880.zip","image":[],"word_id":40158836,"text":"clear","audio":[{"duration":0,"file_path":"f4e2ccbb-f046-4a6d-ad63-c0d9146a2cac.mp3","score":0,"voices_type_id":65,"tag_title":"clear","link":"audio/f4e2ccbb-f046-4a6d-ad63-c0d9146a2cac.mp3","name_original":"","voices_id":65,"id":258305,"sync_data":""}],"video":[],"type":"question","order":0},{"path":"3332ffe6-3672-42f8-979a-4771cda84417_360881.zip","image":[],"word_id":40158837,"text":"c","audio":[{"duration":0,"file_path":"75762f07-fb9f-43a7-ab04-3d9180f33560.mp3","score":0,"voices_type_id":65,"tag_title":"c","link":"audio/75762f07-fb9f-43a7-ab04-3d9180f33560.mp3","name_original":"","voices_id":65,"id":258306,"sync_data":""}],"video":[],"type":"phonic","order":0},{"path":"dc48718a-ce8a-46ec-a27f-bd6a9302fb52_360882.zip","image":[],"word_id":40158838,"text":"l","audio":[{"duration":0,"file_path":"7df2ed45-514d-4735-90b5-dceb6ad558b3.mp3","score":0,"voices_type_id":65,"tag_title":"l","link":"audio/7df2ed45-514d-4735-90b5-dceb6ad558b3.mp3","name_original":"","voices_id":65,"id":258307,"sync_data":""}],"video":[],"type":"phonic","order":0},{"path":"38fc5fbb-8057-485c-bbfb-228dcb37cc98_360883.zip","image":[],"word_id":40158839,"text":"ear","audio":[{"duration":0,"file_path":"1e87591f-ba15-4fba-919a-9aeb3da53afb.mp3","score":0,"voices_type_id":65,"tag_title":"ear","link":"audio/1e87591f-ba15-4fba-919a-9aeb3da53afb.mp3","name_original":"","voices_id":65,"id":258308,"sync_data":""}],"video":[],"type":"phonic","order":0}],"phonic":{},"order":1}],"thumb_start":{}},{"file_zip":"1529262-57586-epn.zip","story_name":{},"thumb_end":{},"background":"","act_id":1529262,"id":1000162,"turn":[{"right_answer":[],"word":[{"path":"1a8f78d4-6393-4710-a261-65258f57123a_360973.zip","image":[],"word_id":40158929,"text":"steer","audio":[{"duration":0,"file_path":"9240dff0-0f5d-414c-acc5-c6854a86ab61.mp3","score":0,"voices_type_id":65,"tag_title":"steer","link":"audio/9240dff0-0f5d-414c-acc5-c6854a86ab61.mp3","name_original":"","voices_id":65,"id":258402,"sync_data":""}],"video":[],"type":"question","order":0},{"path":"be9e08f0-e198-4898-b136-19a7e9ec15a5_360974.zip","image":[],"word_id":40158930,"text":"st","audio":[{"duration":0,"file_path":"95ef397b-d9b2-466e-baaf-d190817bad9a.mp3","score":0,"voices_type_id":65,"tag_title":"st","link":"audio/95ef397b-d9b2-466e-baaf-d190817bad9a.mp3","name_original":"","voices_id":65,"id":258403,"sync_data":""}],"video":[],"type":"phonic","order":0},{"path":"c9c5a24a-5ab7-49ba-980b-8156f714fa13_360975.zip","image":[],"word_id":40158931,"text":"eer","audio":[{"duration":0,"file_path":"5d22d42d-769a-4251-8133-530b5b1956ab.mp3","score":0,"voices_type_id":65,"tag_title":"eer","link":"audio/5d22d42d-769a-4251-8133-530b5b1956ab.mp3","name_original":"","voices_id":65,"id":258404,"sync_data":""}],"video":[],"type":"phonic","order":0}],"phonic":{},"order":1}],"thumb_start":{}},{"file_zip":"1529288-57631-znh.zip","story_name":{},"thumb_end":{},"background":"","act_id":1529288,"id":1000162,"turn":[{"right_answer":[],"word":[{"path":"bb5b98b6-fdbf-467c-b6c2-8462b9462319_360330.zip","image":[],"word_id":40158286,"text":"silt","audio":[{"duration":0,"file_path":"71861243-16f2-4fdb-be49-8a37569110da.mp3","score":0,"voices_type_id":65,"tag_title":"silt","link":"audio/71861243-16f2-4fdb-be49-8a37569110da.mp3","name_original":"","voices_id":65,"id":257772,"sync_data":""}],"video":[],"type":"question","order":0},{"path":"d7446120-c2dd-4d15-9a9c-028db864475c_360331.zip","image":[],"word_id":40158287,"text":"s","audio":[{"duration":0,"file_path":"f8b8dbcb-c93b-43f4-98fd-da3bbbcfb0b0.mp3","score":0,"voices_type_id":65,"tag_title":"s","link":"audio/f8b8dbcb-c93b-43f4-98fd-da3bbbcfb0b0.mp3","name_original":"","voices_id":65,"id":257773,"sync_data":""}],"video":[],"type":"phonic","order":0},{"path":"c13f67d3-fbb4-455c-bec7-f35c4065b65d_360332.zip","image":[],"word_id":40158288,"text":"i","audio":[{"duration":0,"file_path":"42bf9267-fc20-4a74-be8b-c8462fd9cf9e.mp3","score":0,"voices_type_id":65,"tag_title":"i","link":"audio/42bf9267-fc20-4a74-be8b-c8462fd9cf9e.mp3","name_original":"","voices_id":65,"id":257774,"sync_data":""}],"video":[],"type":"phonic","order":0},{"path":"d1f54ab5-063f-4373-af4c-68afca4c1ab7_360333.zip","image":[],"word_id":40158289,"text":"lt","audio":[{"duration":0,"file_path":"d210d7fb-4ca1-40c3-96ca-bb8924e0eae4.mp3","score":0,"voices_type_id":65,"tag_title":"lt","link":"audio/d210d7fb-4ca1-40c3-96ca-bb8924e0eae4.mp3","name_original":"","voices_id":65,"id":257775,"sync_data":""}],"video":[],"type":"phonic","order":0}],"phonic":{},"order":1}],"thumb_start":{}},{"file_zip":"1529322-57646-aws.zip","story_name":{},"thumb_end":{},"background":"","act_id":1529322,"id":1000162,"turn":[{"right_answer":[],"word":[{"path":"1ddb2857-4fce-4758-97a6-ebcee54bbf9f_360124.zip","image":[],"word_id":40158080,"text":"left","audio":[{"duration":0,"file_path":"e8d17a65-6684-4943-a3da-8638778ef4ba.mp3","score":0,"voices_type_id":65,"tag_title":"left","link":"audio/e8d17a65-6684-4943-a3da-8638778ef4ba.mp3","name_original":"","voices_id":65,"id":257571,"sync_data":""}],"video":[],"type":"question","order":0},{"path":"3f63afe6-1a2c-48e9-9b42-85de7ac139f7_360125.zip","image":[],"word_id":40158081,"text":"l","audio":[{"duration":0,"file_path":"0590c044-db1c-4276-9764-305e60d2bd22.mp3","score":0,"voices_type_id":65,"tag_title":"l","link":"audio/0590c044-db1c-4276-9764-305e60d2bd22.mp3","name_original":"","voices_id":65,"id":257572,"sync_data":""}],"video":[],"type":"phonic","order":0},{"path":"c45c9e78-df2d-4631-9d2b-91a194b3c8d1_360126.zip","image":[],"word_id":40158082,"text":"e","audio":[{"duration":0,"file_path":"7b241661-80f4-4069-aaad-e670e35f1581.mp3","score":0,"voices_type_id":65,"tag_title":"e","link":"audio/7b241661-80f4-4069-aaad-e670e35f1581.mp3","name_original":"","voices_id":65,"id":257573,"sync_data":""}],"video":[],"type":"phonic","order":0},{"path":"03400e38-dad9-4dad-ba3b-2390a97fe261_360127.zip","image":[],"word_id":40158083,"text":"ft","audio":[{"duration":0,"file_path":"9abd530d-f1d1-4be7-9444-81ef887b9f1b.mp3","score":0,"voices_type_id":65,"tag_title":"ft","link":"audio/9abd530d-f1d1-4be7-9444-81ef887b9f1b.mp3","name_original":"","voices_id":65,"id":257574,"sync_data":""}],"video":[],"type":"phonic","order":0}],"phonic":{},"order":1}],"thumb_start":{}},{"file_zip":"1529331-57616-hfn.zip","story_name":{},"thumb_end":{},"background":"","act_id":1529331,"id":1000162,"turn":[{"right_answer":[],"word":[{"path":"38ec5024-bf16-435b-a558-5a8a7ed2f623_360545.zip","image":[],"word_id":40158501,"text":"silk","audio":[{"duration":0,"file_path":"f2151a49-4e73-4d5e-a538-98b140f11330.mp3","score":0,"voices_type_id":65,"tag_title":"silk","link":"audio/f2151a49-4e73-4d5e-a538-98b140f11330.mp3","name_original":"","voices_id":65,"id":257983,"sync_data":""}],"video":[],"type":"question","order":0},{"path":"05fc5474-b738-4b25-969e-6e2b639714de_360546.zip","image":[],"word_id":40158502,"text":"s","audio":[{"duration":0,"file_path":"c55e7121-d251-4c44-a327-131195dd19be.mp3","score":0,"voices_type_id":65,"tag_title":"s","link":"audio/c55e7121-d251-4c44-a327-131195dd19be.mp3","name_original":"","voices_id":65,"id":257984,"sync_data":""}],"video":[],"type":"phonic","order":0},{"path":"078464df-79b2-419b-a867-33aa4f4ea555_360547.zip","image":[],"word_id":40158503,"text":"i","audio":[{"duration":0,"file_path":"94f6e4af-8250-4f95-b244-9a75fad830d5.mp3","score":0,"voices_type_id":65,"tag_title":"i","link":"audio/94f6e4af-8250-4f95-b244-9a75fad830d5.mp3","name_original":"","voices_id":65,"id":257985,"sync_data":""}],"video":[],"type":"phonic","order":0},{"path":"35d61359-f3a1-444d-b667-78ea6f2e64e1_360548.zip","image":[],"word_id":40158504,"text":"lk","audio":[{"duration":0,"file_path":"36d52c52-eb97-4e1c-b276-c9c7760f34e3.mp3","score":0,"voices_type_id":65,"tag_title":"lk","link":"audio/36d52c52-eb97-4e1c-b276-c9c7760f34e3.mp3","name_original":"","voices_id":65,"id":257986,"sync_data":""}],"video":[],"type":"phonic","order":0}],"phonic":{},"order":1}],"thumb_start":{}},{"file_zip":"1529361-57609-jax.zip","story_name":{},"thumb_end":{},"background":"","act_id":1529361,"id":1000162,"turn":[{"right_answer":[],"word":[{"path":"3e1555df-86e8-4b9e-a90d-51599f7ae573_360667.zip","image":[],"word_id":40158623,"text":"hair","audio":[{"duration":0,"file_path":"400b4382-6f9a-450c-abbc-00311689560c.mp3","score":0,"voices_type_id":65,"tag_title":"hair","link":"audio/400b4382-6f9a-450c-abbc-00311689560c.mp3","name_original":"","voices_id":65,"id":258096,"sync_data":""}],"video":[],"type":"question","order":0},{"path":"b10faaa8-b66a-4403-a2b9-08497180e23c_360668.zip","image":[],"word_id":40158624,"text":"h","audio":[{"duration":0,"file_path":"78ed9234-98de-4821-9d9d-c7b6ee9889e8.mp3","score":0,"voices_type_id":65,"tag_title":"h","link":"audio/78ed9234-98de-4821-9d9d-c7b6ee9889e8.mp3","name_original":"","voices_id":65,"id":258097,"sync_data":""}],"video":[],"type":"phonic","order":0},{"path":"9025cbfe-254e-4131-bcaa-1defeffd6135_360669.zip","image":[],"word_id":40158625,"text":"air","audio":[{"duration":0,"file_path":"76027c43-cc1f-4889-945b-ee0830887ece.mp3","score":0,"voices_type_id":65,"tag_title":"air","link":"audio/76027c43-cc1f-4889-945b-ee0830887ece.mp3","name_original":"","voices_id":65,"id":258098,"sync_data":""}],"video":[],"type":"phonic","order":0}],"phonic":{},"order":1}],"thumb_start":{}},{"file_zip":"1529373-57601-upy.zip","story_name":{},"thumb_end":{},"background":"","act_id":1529373,"id":1000162,"turn":[{"right_answer":[],"word":[{"path":"759b1df8-ffc6-4ebe-a3f5-aa01696da354_360758.zip","image":[],"word_id":40158714,"text":"stare","audio":[{"duration":0,"file_path":"8614f660-4a32-4c41-bf41-a4543e0a68c9.mp3","score":0,"voices_type_id":65,"tag_title":"stare","link":"audio/8614f660-4a32-4c41-bf41-a4543e0a68c9.mp3","name_original":"","voices_id":65,"id":258191,"sync_data":""}],"video":[],"type":"question","order":0},{"path":"c0cd9d83-d186-4870-847f-53c6bb7a4ed3_360759.zip","image":[],"word_id":40158715,"text":"st","audio":[{"duration":0,"file_path":"39c0b389-1ffa-4244-9026-8f4e7d653400.mp3","score":0,"voices_type_id":65,"tag_title":"st","link":"audio/39c0b389-1ffa-4244-9026-8f4e7d653400.mp3","name_original":"","voices_id":65,"id":258192,"sync_data":""}],"video":[],"type":"phonic","order":0},{"path":"a75cc788-a93d-4942-aff7-63d0cd9cea31_360760.zip","image":[],"word_id":40158716,"text":"are","audio":[{"duration":0,"file_path":"49d0faca-bd00-48cd-8f34-c7dbf4dc1e8c.mp3","score":0,"voices_type_id":65,"tag_title":"are","link":"audio/49d0faca-bd00-48cd-8f34-c7dbf4dc1e8c.mp3","name_original":"","voices_id":65,"id":258193,"sync_data":""}],"video":[],"type":"phonic","order":0}],"phonic":{},"order":1}],"thumb_start":{}},{"file_zip":"1529384-57654-bzj.zip","story_name":{},"thumb_end":{},"background":"","act_id":1529384,"id":1000162,"turn":[{"right_answer":[],"word":[{"path":"6f3e5659-a971-4ea8-a422-288b235af386_360033.zip","image":[],"word_id":40157989,"text":"pump","audio":[{"duration":0,"file_path":"c2bbc816-fe49-4de1-ad50-fec17421518a.mp3","score":0,"voices_type_id":65,"tag_title":"pump","link":"audio/c2bbc816-fe49-4de1-ad50-fec17421518a.mp3","name_original":"","voices_id":65,"id":257476,"sync_data":""}],"video":[],"type":"question","order":0},{"path":"6bbfa496-a14f-4d96-acf5-bb2209dfd385_360034.zip","image":[],"word_id":40157990,"text":"p","audio":[{"duration":0,"file_path":"f6850600-e886-4d3e-904f-35e84d4e4f5b.mp3","score":0,"voices_type_id":65,"tag_title":"p","link":"audio/f6850600-e886-4d3e-904f-35e84d4e4f5b.mp3","name_original":"","voices_id":65,"id":257477,"sync_data":""}],"video":[],"type":"phonic","order":0},{"path":"2e26e893-548d-4559-a8ff-c8d4e4519ff3_360035.zip","image":[],"word_id":40157991,"text":"u","audio":[{"duration":0,"file_path":"776ef288-e07d-4eba-b07c-b07e5c783f5d.mp3","score":0,"voices_type_id":65,"tag_title":"u","link":"audio/776ef288-e07d-4eba-b07c-b07e5c783f5d.mp3","name_original":"","voices_id":65,"id":257478,"sync_data":""}],"video":[],"type":"phonic","order":0},{"path":"dfe8d063-f362-4575-be91-f152a45ca931_360036.zip","image":[],"word_id":40157992,"text":"mp","audio":[{"duration":0,"file_path":"27214ef4-0353-42b6-93ae-84354ba3b096.mp3","score":0,"voices_type_id":65,"tag_title":"mp","link":"audio/27214ef4-0353-42b6-93ae-84354ba3b096.mp3","name_original":"","voices_id":65,"id":257479,"sync_data":""}],"video":[],"type":"phonic","order":0}],"phonic":{},"order":1}],"thumb_start":{}}]